Metadata-Version: 1.1
Name: tensorgraphx
Version: 6.0.0
Summary: A high level tensorflow library for building deep learning models
Home-page: https://github.com/hycis/TensorGraphX
Author: Wu Zhen Zhou
Author-email: hyciswu@gmail.com
License: Apache 2.0, see LICENCE
Download-URL: https://github.com/hycis/TensorGraphX/tarball/6.0.0
Platform: UNKNOWN
